README.md
setup.py
matts_majestic_monads.egg-info/PKG-INFO
matts_majestic_monads.egg-info/SOURCES.txt
matts_majestic_monads.egg-info/dependency_links.txt
matts_majestic_monads.egg-info/top_level.txt
monads/__init__.py
monads/base.py
monads/either.py
monads/function.py
monads/list.py
monads/maybe.py
monads/operators.py
tests/__init__.py
tests/test_either.py
tests/test_either_applicative.py
tests/test_either_functor.py
tests/test_either_monad.py
tests/test_function.py
tests/test_list.py
tests/test_list_applicative.py
tests/test_list_functor.py
tests/test_list_monad.py
tests/test_maybe.py
tests/test_maybe_applicative.py
tests/test_maybe_functor.py
tests/test_maybe_monad.py