Metadata-Version: 2.1
Name: matts-majestic-monads
Version: 0.0.5
Summary: Monadic data structures
Home-page: https://gitlab.com/matthewfranglen/matts-majestic-monads
Author: Matthew Franglen
Author-email: matthew@franglen.org
License: UNKNOWN
Platform: UNKNOWN
